{
  "@context": "https://schema.org",
  "@type": "TechArticle",
  "headline": "Gap: most content plans lack a **decision framework for updating existing pages vs. creating new ones**",
  "name": "Gap: most content plans lack a **decision framework for updating existing pages vs. creating new ones**",
  "about": "AI citations generation",
  "articleSection": "Competitive question gap research",
  "description": "The competitive gap is that many businesses do not understand **how to choose between creating new content and upgrading existing content**. Most articles simpl",
  "articleBody": "The competitive gap is that many businesses do not understand **how to choose between creating new content and upgrading existing content**. Most articles simply say to do both, but that is not an operational plan. A better rule is to start with pages that already rank, already get impressions, or already cover a topic adjacent to a citation-winning query. Those pages have the best chance of moving into AI answers with targeted edits. New content makes more sense when there is a clear prompt with no existing coverage on your site or when the query requires a distinct format, such as a comparison, calculator, or playbook. This distinction matters because AI citation generation is usually won by pages that are both relevant and efficient to extract. Upgrading a near-win page often delivers faster results than publishing a brand-new article into a crowded field. The pitfall is creating dozens of new posts that fragment topical authority and never receive enough depth or trust to be cited. A page-level decision framework is usually more effective than a volume-based content calendar.",
  "keywords": "AI citations generation, procedural",
  "url": "aeoptimizer.com/research-gap/ai-citations-generation-should-i-update-existing-pages-or-create-new-ones-to-get-mor"
}